pyteledb/__init__.py
pyteledb/exceptions.py
pyteledb/version.py
pyteledb/cache/__init__.py
pyteledb/cache/base.py
pyteledb/cache/memory.py
pyteledb/cache/sqlite.py
pyteledb/core/__init__.py
pyteledb/core/database.py
pyteledb/core/locks.py
pyteledb/core/pointers.py
pyteledb/core/record.py
pyteledb/core/repair.py
pyteledb/core/root.py
pyteledb/ops/__init__.py
pyteledb/ops/metrics.py
pyteledb/ops/queue.py
pyteledb/ops/throttling.py
pyteledb/storage/__init__.py
pyteledb/storage/checksum.py
pyteledb/storage/schema.py
pyteledb/storage/serializer.py
pyteledb/storage/versioning.py
pyteledb/telegram/__init__.py
pyteledb/telegram/client.py
pyteledb/telegram/errors.py
pyteledb/telegram/files.py
pyteledb/telegram/messages.py
pyteledb/telegram/pins.py
pyteledb/utils/__init__.py
pyteledb/utils/ids.py
pyteledb/utils/logging.py
pyteledb/utils/time.py
pyteledb-0.1.0.dist-info/METADATA
pyteledb-0.1.0.dist-info/WHEEL
pyteledb-0.1.0.dist-info/licenses/LICENSE
pyteledb-0.1.0.dist-info/RECORD
