Metadata-Version: 2.4
Name: pyteledb
Version: 0.1.0
Summary: A Telegram-native embedded database for Telegram bots
Project-URL: Homepage, https://github.com/SilentDemonSD/pyteledb
Project-URL: Documentation, https://github.com/SilentDemonSD/pyteledb#readme
Project-URL: Repository, https://github.com/SilentDemonSD/pyteledb
Project-URL: Issues, https://github.com/SilentDemonSD/pyteledb/issues
Author: pyteledb contributors
License-Expression: GPL-3.0-or-later
License-File: LICENSE
Keywords: bot,database,embedded,persistence,telegram
Classifier: Development Status :: 3 - Alpha
Classifier: Framework :: AsyncIO
Classifier: Intended Audience :: Developers
Classifier: License :: OSI Approved :: GNU General Public License v3 or later (GPLv3+)
Classifier: Operating System :: OS Independent
Classifier: Programming Language :: Python :: 3
Classifier: Programming Language :: Python :: 3.10
Classifier: Programming Language :: Python :: 3.11
Classifier: Programming Language :: Python :: 3.12
Classifier: Topic :: Communications :: Chat
Classifier: Topic :: Database
Classifier: Typing :: Typed
Requires-Python: >=3.10
Requires-Dist: httpx>=0.25.0
Provides-Extra: dev
Requires-Dist: mypy>=1.5.0; extra == 'dev'
Requires-Dist: pytest-asyncio>=0.21.0; extra == 'dev'
Requires-Dist: pytest>=7.4.0; extra == 'dev'
Requires-Dist: ruff>=0.1.0; extra == 'dev'
Provides-Extra: sqlite
Requires-Dist: aiosqlite>=0.19.0; extra == 'sqlite'
